Metadata-Version: 1.1
Name: dashmadeline
Version: 0.0.1
Summary: Project Description
Home-page: UNKNOWN
Author: Eric Yi <hy2646@columbia.edu>
Author-email: UNKNOWN
License: MIT
Platform: UNKNOWN
Classifier: Framework :: Dash
